Workbook

Sheet START HERE
A1: CONTRACTOR PROFIT TOOLKIT | 1.2
A3: STEP | B3: WHAT TO DO | C3: IMPORTANT DETAIL
A4: 01 | B4: Enter project name, overhead budget and contingency on Project Setup. | C4: All demo numbers are fictional and must be replaced.
A5: 02 | B5: Build your base quote in Estimate with quantities, costs and markups. | C5: Markup is a percentage of COST, not sales margin.
A6: 03 | B6: Log every real expense ONCE in Actual Costs. | C6: Include approved change-order expenses here; do not separately add change-order estimated costs to actuals.
A7: 04 | B7: Track changes in Change Orders and mark their actual status. | C7: Only Approved changes increase contracted revenue.
A8: 05 | B8: Enter customer payments in Payments. | C8: Revenue contracted is not the same thing as money collected.
A9: 06 | B9: Review Dashboard warnings and contribution margins. | C9: Incomplete job costs overstate profit. Receipts less incurred costs is NOT cash flow.
A10: 07 | B10: Use USD; enter dates as real Excel dates. | C10: Customer tax excluded. Costs include nonrecoverable purchase taxes. Negative payment = refund.
A11: 08 | B11: Duplicate this workbook per project. | C11: Fixed capacity: 100 estimate, 200 costs, 100 changes, 100 payment rows. Do not add rows.
A12: 09 | B12: Check unusual expense classifications and pending changes. | C12: Spreadsheet is a management aid, not tax, legal, accounting or certified estimating advice.
A13: 10 | B13: Store your files securely and back up regularly. | C13: Edit blue cells. Sheet protection prevents accidents, not unauthorized access. No password needed to unprotect.

Sheet Project Setup
A1: PROJECT SETUP | EDIT BLUE CELLS
A3: FIELD | B3: VALUE | C3: NOTES
A4: Project name | C4: Replace before production use
A5: Client name | C5: Replace with your client
A6: Project ID | C6: One project per workbook
A7: Estimated direct overhead ($) | B7: 0 | C7: Project-attributable supervision, permits, overhead; not included in Estimate direct line items
A8: Actual overhead incurred ($) | B8: 0 | C8: Enter project-attributable overhead already incurred; exclude amounts also logged under Actual Costs
A9: Contingency rate | B9: 0 | C9: Contingency is a planning reserve; not income or an actual expense
A10: Sales tax allowance ($) | B10: 0 | C10: Excluded informational allowance. Enter all other figures consistently net of customer sales tax.
A11: Notes | C11: Use local applicable rules and your accountant
A12: Reporting date | C12: As-of date used for illustrative tracking
A13: Target contribution margin | B13: 0.2 | C13: Benchmark after project overhead; excludes unallocated company overhead and tax.

Sheet Estimate
A1: BASE ESTIMATE | DIRECT LINE-ITEM COSTS
A3: LINE ITEM | B3: CATEGORY | C3: QUANTITY | D3: UNIT COST ($) | E3: DIRECT COST ($) | F3: MARKUP % | G3: SELL PRICE ($) | H3: NOTES
E4: =IF(OR(C4="",D4=""),"",ROUND(C4*D4,2)) | G4: =IF(E4="","",ROUND(E4*(1+IF(F4="",0,F4)),2))
E5: =IF(OR(C5="",D5=""),"",ROUND(C5*D5,2)) | G5: =IF(E5="","",ROUND(E5*(1+IF(F5="",0,F5)),2))
E6: =IF(OR(C6="",D6=""),"",ROUND(C6*D6,2)) | G6: =IF(E6="","",ROUND(E6*(1+IF(F6="",0,F6)),2))
E7: =IF(OR(C7="",D7=""),"",ROUND(C7*D7,2)) | G7: =IF(E7="","",ROUND(E7*(1+IF(F7="",0,F7)),2))
E8: =IF(OR(C8="",D8=""),"",ROUND(C8*D8,2)) | G8: =IF(E8="","",ROUND(E8*(1+IF(F8="",0,F8)),2))
E9: =IF(OR(C9="",D9=""),"",ROUND(C9*D9,2)) | G9: =IF(E9="","",ROUND(E9*(1+IF(F9="",0,F9)),2))
E10: =IF(OR(C10="",D10=""),"",ROUND(C10*D10,2)) | G10: =IF(E10="","",ROUND(E10*(1+IF(F10="",0,F10)),2))
E11: =IF(OR(C11="",D11=""),"",ROUND(C11*D11,2)) | G11: =IF(E11="","",ROUND(E11*(1+IF(F11="",0,F11)),2))
E12: =IF(OR(C12="",D12=""),"",ROUND(C12*D12,2)) | G12: =IF(E12="","",ROUND(E12*(1+IF(F12="",0,F12)),2))
E13: =IF(OR(C13="",D13=""),"",ROUND(C13*D13,2)) | G13: =IF(E13="","",ROUND(E13*(1+IF(F13="",0,F13)),2))
E14: =IF(OR(C14="",D14=""),"",ROUND(C14*D14,2)) | G14: =IF(E14="","",ROUND(E14*(1+IF(F14="",0,F14)),2))
E15: =IF(OR(C15="",D15=""),"",ROUND(C15*D15,2)) | G15: =IF(E15="","",ROUND(E15*(1+IF(F15="",0,F15)),2))
... E103: =IF(OR(C103="",D103=""),"",ROUND(C103*D103,2)) | G103: =IF(E103="","",ROUND(E103*(1+IF(F103="",0,F103)),2))

Sheet Actual Costs
A1: ACTUAL COST LEDGER | ENTER EACH COST ONCE
A3: DATE | B3: DESCRIPTION | C3: CATEGORY | D3: QTY | E3: UNIT COST ($) | F3: ACTUAL COST ($) | G3: REFERENCE | H3: BASE / CHANGE
F4: =IF(OR(D4="",E4=""),"",ROUND(D4*E4,2))
F5: =IF(OR(D5="",E5=""),"",ROUND(D5*E5,2))
F6: =IF(OR(D6="",E6=""),"",ROUND(D6*E6,2))
F7: =IF(OR(D7="",E7=""),"",ROUND(D7*E7,2))
F8: =IF(OR(D8="",E8=""),"",ROUND(D8*E8,2))
F9: =IF(OR(D9="",E9=""),"",ROUND(D9*E9,2))
F10: =IF(OR(D10="",E10=""),"",ROUND(D10*E10,2))
F11: =IF(OR(D11="",E11=""),"",ROUND(D11*E11,2))
F12: =IF(OR(D12="",E12=""),"",ROUND(D12*E12,2))
F13: =IF(OR(D13="",E13=""),"",ROUND(D13*E13,2))
F14: =IF(OR(D14="",E14=""),"",ROUND(D14*E14,2))
F15: =IF(OR(D15="",E15=""),"",ROUND(D15*E15,2))
... F203: =IF(OR(D203="",E203=""),"",ROUND(D203*E203,2))

Sheet Change Orders
A1: CHANGE ORDERS | APPROVED REVENUE ONLY
A3: CHANGE ID | B3: DESCRIPTION | C3: STATUS | D3: ADDED REVENUE ($) | E3: EST. CHANGE COST ($) | F3: EST. CONTRIBUTION ($) | G3: NOTES
F4: =IF(C4="Approved",IF(OR(D4="",E4=""),"",ROUND(D4-E4,2)),0) -> 0
F5: =IF(C5="Approved",IF(OR(D5="",E5=""),"",ROUND(D5-E5,2)),0) -> 0
F6: =IF(C6="Approved",IF(OR(D6="",E6=""),"",ROUND(D6-E6,2)),0) -> 0
F7: =IF(C7="Approved",IF(OR(D7="",E7=""),"",ROUND(D7-E7,2)),0) -> 0
F8: =IF(C8="Approved",IF(OR(D8="",E8=""),"",ROUND(D8-E8,2)),0) -> 0
F9: =IF(C9="Approved",IF(OR(D9="",E9=""),"",ROUND(D9-E9,2)),0) -> 0
F10: =IF(C10="Approved",IF(OR(D10="",E10=""),"",ROUND(D10-E10,2)),0) -> 0
F11: =IF(C11="Approved",IF(OR(D11="",E11=""),"",ROUND(D11-E11,2)),0) -> 0
F12: =IF(C12="Approved",IF(OR(D12="",E12=""),"",ROUND(D12-E12,2)),0) -> 0
F13: =IF(C13="Approved",IF(OR(D13="",E13=""),"",ROUND(D13-E13,2)),0) -> 0
F14: =IF(C14="Approved",IF(OR(D14="",E14=""),"",ROUND(D14-E14,2)),0) -> 0
F15: =IF(C15="Approved",IF(OR(D15="",E15=""),"",ROUND(D15-E15,2)),0) -> 0
... F103: =IF(C103="Approved",IF(OR(D103="",E103=""),"",ROUND(D103-E103,2)),0) -> 0

Sheet Payments
A1: PAYMENTS RECEIVED | CASH ACTUALLY COLLECTED
A3: DATE | B3: PAYMENT REFERENCE | C3: AMOUNT RECEIVED ($) | D3: PAYMENT METHOD | E3: NOTES

Sheet Dashboard
A1: PROJECT DASHBOARD | ONE JOB AT A TIME
A3: METRIC | B3: VALUE | C3: WHAT THIS MEANS
A4: Base quoted revenue | B4: =SUM('Estimate'!G4:G103) -> 0 | C4: Base quoted selling prices, excluding pending changes
A5: Approved change revenue | B5: =SUMIF('Change Orders'!C4:C103,"Approved",'Change Orders'!D4:D103) -> 0 | C5: Only approved changes count as contract revenue
A6: Contracted revenue | B6: =B4+B5 -> 0 | C6: Base revenue plus approved change orders; not cash collected
A7: Estimated base direct costs | B7: =SUM('Estimate'!E4:E103) -> 0 | C7: Estimated direct costs from base estimate
A8: Estimated approved change costs | B8: =SUMIF('Change Orders'!C4:C103,"Approved",'Change Orders'!E4:E103) -> 0 | C8: Estimates only; NOT added to actual costs
A9: Budgeted project overhead | B9: ='Project Setup'!B7 -> 0 | C9: Planned overhead directly attributable to this project
A10: Estimated total cost | B10: =SUM(B7:B9) -> 0 | C10: Estimated base direct + approved change + overhead
A11: Budgeted job contribution | B11: =B6-B10 -> 0 | C11: Contract revenue less estimated direct costs and attributable overhead; excludes corporate overhead and taxes.
A12: Budgeted margin | B12: =IF(B6=0,"",B11/B6) | C12: Contribution / contracted revenue. Blank when revenue is zero; markup is cost-based.
A13: Logged actual direct cost | B13: =SUM('Actual Costs'!F4:F203) -> 0 | C13: All actual cost entries, including change work where incurred
A14: Actual overhead incurred | B14: ='Project Setup'!B8 -> 0 | C14: Actual attributable overhead not already logged above
A15: Total incurred costs | B15: =B13+B14 -> 0 | C15: Costs incurred to date; incomplete projects omit future costs
A16: Contract less costs incurred | B16: =B6-B15 -> 0 | C16: Not final profit if job is incomplete or unbilled costs remain
A17: Incurred-cost margin | B17: =IF(B6=0,"",B16/B6) | C17: Provisional contribution / contract. Blank when revenue is zero; no completion forecast.
A18: Customer payments received | B18: =SUM('Payments'!C4:C103) -> 0 | C18: Actual money collected from customer
A19: Uncollected contract balance | B19: =B6-B18 -> 0 | C19: Negative means receipts exceed contract. Not accounts receivable or an invoice aging report.
A20: Receipts less incurred costs | B20: =B18-B15 -> 0 | C20: NOT cash flow: expenses may be unpaid. No expense-payment ledger is included.
A21: Cost still available vs budget | B21: =B10-B15 -> 0 | C21: Negative means incurred costs exceed total estimated budget
A22: Contingency allowance | B22: =ROUND(B10*'Project Setup'!B9,2) -> 0 | C22: Optional planning reserve, NOT automatically added to contracted revenue
A23: Margin target | B23: ='Project Setup'!B13 -> 0.2 | C23: Desired project margin; assess again when the job is complete
A24: Entry warnings | B24: =SUMPRODUCT(--(Estimate!A4:A103<>""),--(Estimate!C4:C103=""))+SUMPRODUCT(--(Estimate!A4:A103<>""),--(Estimate!D4:D103=""))+SUMPRODUCT(--('Actual Costs'!B4:B203<>""),--('Actual Costs'!D4:D203=""))+SUMPRODUCT(--('Actual Costs'!B4:B203<>""),--('Actual Costs'!E4:E203=""))+SUMPRODUCT(--('Change Orders'!C4:C103="Approved"),--('Change Orders'!D4:D103=""))+SUMPRODUCT(--('Change Orders'!C4:C103="Approved"),--('Change Orders'!E4:E103=""))+SUMPRODUCT(--(Payments!B4:B103<>""),--(Payments!C4:C103="")) -> 0 | C24: Missing required numeric fields on described entries. Counts fields, not rows. Review before relying on totals.
A26: IMPORTANT | B26: Revenue is contracted, not necessarily invoiced or collected.
A27: COST POLICY | B27: Change-order actual costs belong in Actual Costs exactly once.
A28: STATUS | B28: Provisional until every cost is recorded. Blank margin means zero contract revenue.

Sheet RELEASE NOTES
A1: CONTRACTOR TOOLKIT — RELEASE NOTES
A2: Version | B2: 1.2 production package
A3: Scope | B3: Single project per workbook; USD; Excel formulas
A4: Demo data | B4: All example customers and transactions are fictional
A5: Profit warning | B5: Projected margin is not realized profit; verify all costs and revenue
A6: Tax warning | B6: No sales tax, income tax, payroll tax or jurisdiction-specific compliance calculated
A7: License | B7: One purchasing business may reuse for its own jobs. No redistribution or resale. See included license.
